crawl4aicloud/__init__.py
crawl4aicloud/client.py
crawl4aicloud/enums.py
crawl4aicloud/exceptions.py
crawl4aicloud/schemas.py
crawl4aicloud/utils.py
crawl4aicloud-1.0.0.dist-info/METADATA
crawl4aicloud-1.0.0.dist-info/WHEEL
crawl4aicloud-1.0.0.dist-info/entry_points.txt
crawl4aicloud-1.0.0.dist-info/licenses/LICENSE
crawl4aicloud-1.0.0.dist-info/RECORD
