Metadata-Version: 2.4
Name: crawl4aicloud
Version: 1.0.0
Summary: Async python client for crawl4ai-cloud.com API
Author-email: backenders-game <sounnecessary88@gmail.com>
License: MIT
License-File: LICENSE
Requires-Python: >=3.12
Requires-Dist: aiohttp>=3.11.12
Requires-Dist: pydantic>=2.10.6
